parrotschemas/__init__.py
parrotschemas/events_monitoring/__init__.py
parrotschemas/events_monitoring/v1/__init__.py
parrotschemas/events_monitoring/v1/events_pb2.py
parrotschemas/events_monitoring/v1/expectations_pb2.py
parrotschemas-0.1.8.dist-info/METADATA
parrotschemas-0.1.8.dist-info/WHEEL
parrotschemas-0.1.8.dist-info/top_level.txt
parrotschemas-0.1.8.dist-info/RECORD
