Metadata-Version: 2.1
Name: parrotschemas
Version: 0.1.8
Summary: Protobuf schemas for Parrot.
Home-page: https://github.com/parrot-com/schemas
Author: Parrot
Maintainer: Parrot
Project-URL: Source Code, https://github.com/parrot-com/schemas
Keywords: protobuf,schemas
Classifier: Programming Language :: Python :: 3
Classifier: Programming Language :: Python :: 3.6
Classifier: Programming Language :: Python :: 3.7
Classifier: Programming Language :: Python :: 3.8
Classifier: Programming Language :: Python :: 3.9
Requires-Python: >=3.6
Requires-Dist: protobuf (>=3.17.3)
